{
  "title": "What Is JavaScript?",
  "description": "The magical language that makes web pages move!",
  "bgTheme": "city",
  "scenes": [
    {
      "id": 1,
      "type": "intro",
      "duration": 5000,
      "garuchanAnimation": "wave",
      "speech": "Hello! Today, let's learn JavaScript together — the language that powers the web!",
      "background": "city",
      "title": "Welcome to JavaScript!",
      "emoji": "🟨",
      "effects": ["sparkle"]
    },
    {
      "id": 2,
      "type": "lesson",
      "duration": 6000,
      "garuchanAnimation": "float",
      "speech": "JavaScript is the language that makes web pages move and react!",
      "background": "city",
      "title": "The Language of Interactive Web Pages",
      "content": "Buttons, games, animations, and popups on the web often run with JavaScript. Web trio: HTML + CSS + JS!",
      "emoji": "⚡",
      "highlight": "🌐 Web = HTML + CSS + JavaScript"
    },
    {
      "id": 3,
      "type": "lesson",
      "duration": 6000,
      "garuchanAnimation": "bounce",
      "speech": "You can use console.log to show messages for testing and debugging!",
      "background": "classroom",
      "title": "Try console.log",
      "content": "Open the browser developer tools and you will see the message there. That's how developers check their code!",
      "emoji": "🖥️",
      "highlight": "console.log(\"Hello World!\")"
    },
    {
      "id": 4,
      "type": "lesson",
      "duration": 6000,
      "garuchanAnimation": "float",
      "speech": "let and const are two ways to store data in JavaScript!",
      "background": "forest",
      "title": "Variables: let and const",
      "content": "Use 'let' for data that changes, 'const' for data that stays fixed. Clear names make your code readable!",
      "emoji": "📝",
      "highlight": "let age = 10;\nconst name = 'Sam';"
    },
    {
      "id": 5,
      "type": "lesson",
      "duration": 6000,
      "garuchanAnimation": "bounce",
      "speech": "Functions are like recipes. You can reuse them again and again!",
      "background": "ocean",
      "title": "Functions = Magic Recipes",
      "content": "Write a function once, call it many times! This keeps your code clean and reduces mistakes.",
      "emoji": "🧑‍🍳",
      "highlight": "function hello() {\n  alert('Hi!');\n}\nhello();"
    },
    {
      "id": 6,
      "type": "lesson",
      "duration": 6000,
      "garuchanAnimation": "float",
      "speech": "DOM manipulation lets JavaScript change what's on the web page directly!",
      "background": "city",
      "title": "DOM Manipulation",
      "content": "Change text, swap colors, add elements — JavaScript makes websites dynamic and interactive!",
      "emoji": "✏️",
      "highlight": "document.getElementById('title')\n  .textContent = 'New!';"
    },
    {
      "id": 7,
      "type": "lesson",
      "duration": 6000,
      "garuchanAnimation": "bounce",
      "speech": "Event listeners make websites respond to user actions like clicks!",
      "background": "candy",
      "title": "Events = User Actions",
      "content": "Click a button, move a mouse, press a key — these are all 'events' that JavaScript can respond to!",
      "emoji": "👆",
      "highlight": "btn.addEventListener('click',\n  () => alert('Clicked!'));"
    },
    {
      "id": 8,
      "type": "lesson",
      "duration": 6000,
      "garuchanAnimation": "float",
      "speech": "Arrays are lists of values stored in one variable!",
      "background": "classroom",
      "title": "Arrays = Data Collections",
      "content": "Arrays let you store multiple values at once. Access them by index number starting from 0!",
      "emoji": "📋",
      "highlight": "const colors = ['red','blue','green'];\nconsole.log(colors[1]); // blue"
    },
    {
      "id": 9,
      "type": "lesson",
      "duration": 6000,
      "garuchanAnimation": "bounce",
      "speech": "Modern JavaScript has powerful features used by the world's biggest websites!",
      "background": "space",
      "title": "JavaScript in the Real World",
      "content": "Facebook, YouTube, Twitter — almost every major website uses JavaScript. It's one of the most in-demand skills!",
      "emoji": "🌍",
      "highlight": "📱 Web Apps  🎮 Browser Games  🤖 Node.js Servers"
    },
    {
      "id": 10,
      "type": "outro",
      "duration": 0,
      "garuchanAnimation": "bounce",
      "speech": "Nice work! You took your first big step into JavaScript! Keep building!",
      "background": "space",
      "title": "Lesson Complete!",
      "emoji": "🚀",
      "effects": ["confetti", "stars"]
    }
  ]
}
